py3dbc/__init__.py
py3dbc/maritime/__init__.py
py3dbc/maritime/constraints.py
py3dbc/maritime/container.py
py3dbc/maritime/packer.py
py3dbc/maritime/ship.py
py3dbc/physics/__init__.py
py3dbc/physics/stability.py
py3dbc-1.0.0.dist-info/licenses/LICENSE
py3dbc-1.0.0.dist-info/METADATA
py3dbc-1.0.0.dist-info/WHEEL
py3dbc-1.0.0.dist-info/top_level.txt
py3dbc-1.0.0.dist-info/RECORD
