Metadata-Version: 2.4
Name: py3dbc
Version: 1.0.0
Summary: 3D Bin Packing for Containers - Maritime optimization with ship stability physics
Home-page: https://github.com/SarthSatpute/py3dbc
Author: Sarth Satpute
Author-email: your.email@example.com
License: MIT
Project-URL: Bug Tracker, https://github.com/SarthSatpute/py3dbc/issues
Project-URL: Documentation, https://github.com/SarthSatpute/py3dbc#readme
Project-URL: Source Code, https://github.com/SarthSatpute/py3dbc
Keywords: 3d-bin-packing,container-optimization,maritime,ship-stability,logistics,cargo
Classifier: Development Status :: 4 - Beta
Classifier: Intended Audience :: Developers
Classifier: Topic :: Software Development :: Libraries :: Python Modules
Classifier: Topic :: Scientific/Engineering
Classifier: License :: OSI Approved :: MIT License
Classifier: Programming Language :: Python :: 3
Classifier: Programming Language :: Python :: 3.8
Classifier: Programming Language :: Python :: 3.9
Classifier: Programming Language :: Python :: 3.10
Classifier: Programming Language :: Python :: 3.11
Classifier: Operating System :: OS Independent
Requires-Python: >=3.8
License-File: LICENSE
Requires-Dist: py3dbp>=1.1.0
Requires-Dist: pandas>=1.3.0
Requires-Dist: numpy>=1.21.0
Dynamic: author
Dynamic: author-email
Dynamic: classifier
Dynamic: description
Dynamic: description-content-type
Dynamic: home-page
Dynamic: keywords
Dynamic: license
Dynamic: license-file
Dynamic: project-url
Dynamic: requires-dist
Dynamic: requires-python
Dynamic: summary
